README.md
setup.py
Nebula/Nebula.py
Nebula/NebulaCore.py
Nebula/NebulaObject.py
Nebula/__init__.py
Nebula/_autoCFG.py
Nebula/_setup.py
Nebula/nebula.py
TestNeb2.egg-info/PKG-INFO
TestNeb2.egg-info/SOURCES.txt
TestNeb2.egg-info/dependency_links.txt
TestNeb2.egg-info/requires.txt
TestNeb2.egg-info/top_level.txt