Metadata-Version: 2.1
Name: TestNeb2
Version: 0.0.51
Summary: An Engine For Building 2d Games With Python+Pygame-CE.
Home-page: https://github.com/setoyuma/NebulaEngine
Author: Setoichi
Author-email: setoichi.dev@gmail.com
License: MIT
Classifier: Development Status :: 3 - Alpha
